wnetalign/__init__.py
wnetalign/__main__.py
wnetalign/aligner.py
wnetalign/spectrum.py
wnetalign-0.9.6.dist-info/licenses/LICENCE
wnetalign-0.9.6.dist-info/METADATA
wnetalign-0.9.6.dist-info/WHEEL
wnetalign-0.9.6.dist-info/top_level.txt
wnetalign-0.9.6.dist-info/RECORD
